eazydocs/__init__.py
eazydocs/core/__init__.py
eazydocs/core/_parser.py
eazydocs/core/_templates.py
eazydocs/core/_types.py
eazydocs/core/class_type.py
eazydocs/core/example.py
eazydocs/core/functions.py
eazydocs/core/method.py
eazydocs/markdown/__init__.py
eazydocs/markdown/reader.py
eazydocs/markdown/updater.py
eazydocs/markdown/writer.py
eazydocs-25.6.0.dist-info/METADATA
eazydocs-25.6.0.dist-info/WHEEL
eazydocs-25.6.0.dist-info/top_level.txt
eazydocs-25.6.0.dist-info/RECORD
