Metadata-Version: 2.4
Name: eazydocs
Version: 25.6.0
Summary: An easy way to generate code documentation by cutting down repetitive boilerplate input. With as little as the function name and its parameters, you can generate a markdown file that mixes markdown and html formatting to clearly define your code.
Author: Aric Kraft
Project-URL: Homepage, https://github.com/aeazy/eazydocs
Project-URL: Issues, https://github.com/aeazy/eazydocs/issues
Classifier: Programming Language :: Python :: 3
Classifier: License :: OSI Approved :: MIT License
Requires-Python: >=3.11
